sprite_pack/__init__.py
sprite_pack/__main__.py
sprite_pack-0.2.0.dist-info/entry_points.txt
sprite_pack-0.2.0.dist-info/WHEEL
sprite_pack-0.2.0.dist-info/METADATA
sprite_pack-0.2.0.dist-info/RECORD
